Authors
LICENSE
MANIFEST.in
NOTICE
README.rst
setup.py
provision/__init__.py
provision/collections.py
provision/config.py
provision/deploy.py
provision/destroy.py
provision/empty
provision/list.py
provision/nodelib.py
provision/ordered_dict.py
provision/patches.py
provision.egg-info/PKG-INFO
provision.egg-info/SOURCES.txt
provision.egg-info/dependency_links.txt
provision.egg-info/entry_points.txt
provision.egg-info/not-zip-safe
provision.egg-info/requires.txt
provision.egg-info/top_level.txt
provision/defaults/__init__.py
provision/defaults/__init__.pyc
provision/defaults/__pycache__/__init__.cpython-33.pyc
provision/defaults/files/.screenrc
provision/defaults/files/.tmux.conf
provision/defaults/files/init.el
provision/defaults/files/update_jenkins_war.sh
provision/defaults/scripts/apache-proxy.sh
provision/defaults/scripts/bootstrap-python.sh
provision/defaults/scripts/datablox.sh
provision/defaults/scripts/devstack.sh
provision/defaults/scripts/emacs.sh
provision/defaults/scripts/git.sh
provision/defaults/scripts/hudson.sh
provision/defaults/scripts/jenkins.sh
provision/defaults/scripts/jre.sh
provision/defaults/scripts/libcloud-env.sh
provision/defaults/scripts/nginx.sh
provision/defaults/scripts/postfix.sh
provision/defaults/scripts/python-env.sh
provision/defaults/scripts/screen.sh
provision/defaults/scripts/snmpd.sh
provision/defaults/scripts/sun-jre.sh
provision/defaults/scripts/swapfile.sh
provision/defaults/scripts/tz.sh
provision/defaults/scripts/zenoss.sh
provision/defaults/scripts/{}
test/__init__.py
test/test_deploy.py
test/test_destroyabilty.py
test/test_handle_errors.py
test/test_image_from_name.py
test/test_lifecycle.py
test/test_normalize_path.py
test/test_script_templates.py
test/test_size_from_name.py