Metadata-Version: 1.0
Name: provision
Version: 0.9.3-dev
Summary: Create highly customized servers in the cloud
Home-page: https://github.com/genforma/provision
Author: genForma Corporation
Author-email: code@genforma.com
License: Apache V2.0
Platform: UNKNOWN
